configen/__init__.py
configen/config.py
configen/configen.py
configen/samples/__init__.py
configen/samples/user.py
configen/templates/dataclass.j2
configen/templates/sample_config.yaml
hydra_configen-0.9.dev1.dist-info/METADATA
hydra_configen-0.9.dev1.dist-info/WHEEL
hydra_configen-0.9.dev1.dist-info/entry_points.txt
hydra_configen-0.9.dev1.dist-info/top_level.txt
hydra_configen-0.9.dev1.dist-info/RECORD
