Metadata-Version: 2.1
Name: hydra-configen
Version: 0.9.dev1
Summary: UNKNOWN
Home-page: http://hydra.cc
Author: Omry Yadan
Author-email: omry@fb.com
License: UNKNOWN
Platform: UNKNOWN
Requires-Dist: hydra-core (>=1.0.0)
Requires-Dist: jinja2
